element_python_package/__init__.py
element_python_package/modelBuild.py
element_python_package/modelPerformance.py
element_python_package/my_module.py
element_python_package/test.py
element_python_package/weakLabelSupport.py
element_python_package-0.2.11.dist-info/METADATA
element_python_package-0.2.11.dist-info/WHEEL
element_python_package-0.2.11.dist-info/top_level.txt
element_python_package-0.2.11.dist-info/RECORD
