Metadata-Version: 2.1
Name: element-python-package
Version: 0.2.11
Summary: This package contains a collection of tools to help build refined models using techniques from weak supervision. It includes tool from data cleaning to model performance and model report generation.
Home-page: UNKNOWN
Author: Sharadind Peddiraju
Author-email: sharadind.pv@gmail.com
License: UNKNOWN
Platform: UNKNOWN
Requires-Dist: scikit-learn
Requires-Dist: seaborn
Requires-Dist: matplotlib
Requires-Dist: pandas
Requires-Dist: numpy
